<annotation>
    <folder>parking_mag</folder>
    <filename>20230608_110054.jpg</filename>
    <size>
        <width>4000</width>
        <height>3000</height>
        <depth>3</depth>
    </size>
    <object>
        <name>spot</name>
        <pose>Unspecified</pose>
        <truncated>0</truncated>
        <occluded>0</occluded>
        <difficult>0</difficult>
        <bndbox>
            <xmin>3749.062744</xmin>
            <ymin>2077.307617</ymin>
            <xmax>4000.000000</xmax>
            <ymax>2328.223877</ymax>
        </bndbox>
    </object>
    <object>
        <name>spot</name>
        <pose>Unspecified</pose>
        <truncated>0</truncated>
        <occluded>0</occluded>
        <difficult>0</difficult>
        <bndbox>
            <xmin>3431.142334</xmin>
            <ymin>2180.273438</ymin>
            <xmax>3682.079590</xmax>
            <ymax>2431.189697</ymax>
        </bndbox>
    </object>
    <object>
        <name>spot</name>
        <pose>Unspecified</pose>
        <truncated>0</truncated>
        <occluded>0</occluded>
        <difficult>0</difficult>
        <bndbox>
            <xmin>3027.243164</xmin>
            <ymin>2190.270020</ymin>
            <xmax>3278.180420</xmax>
            <ymax>2441.186279</ymax>
        </bndbox>
    </object>
    <object>
        <name>spot</name>
        <pose>Unspecified</pose>
        <truncated>0</truncated>
        <occluded>0</occluded>
        <difficult>0</difficult>
        <bndbox>
            <xmin>437.890747</xmin>
            <ymin>2210.263428</ymin>
            <xmax>688.828003</xmax>
            <ymax>2461.179688</ymax>
        </bndbox>
    </object>
    <object>
        <name>spot</name>
        <pose>Unspecified</pose>
        <truncated>0</truncated>
        <occluded>0</occluded>
        <difficult>0</difficult>
        <bndbox>
            <xmin>916.770996</xmin>
            <ymin>2227.257568</ymin>
            <xmax>1167.708252</xmax>
            <ymax>2478.173828</ymax>
        </bndbox>
    </object>
    <object>
        <name>spot</name>
        <pose>Unspecified</pose>
        <truncated>0</truncated>
        <occluded>0</occluded>
        <difficult>0</difficult>
        <bndbox>
            <xmin>1330.667480</xmin>
            <ymin>2220.260010</ymin>
            <xmax>1581.604736</xmax>
            <ymax>2471.176270</ymax>
        </bndbox>
    </object>
    <object>
        <name>spot</name>
        <pose>Unspecified</pose>
        <truncated>0</truncated>
        <occluded>0</occluded>
        <difficult>0</difficult>
        <bndbox>
            <xmin>1918.520508</xmin>
            <ymin>2241.252930</ymin>
            <xmax>2169.457764</xmax>
            <ymax>2492.169189</ymax>
        </bndbox>
    </object>
    <object>
        <name>spot</name>
        <pose>Unspecified</pose>
        <truncated>0</truncated>
        <occluded>0</occluded>
        <difficult>0</difficult>
        <bndbox>
            <xmin>2131.467285</xmin>
            <ymin>2240.253418</ymin>
            <xmax>2382.404541</xmax>
            <ymax>2491.169678</ymax>
        </bndbox>
    </object>
    <object>
        <name>spot</name>
        <pose>Unspecified</pose>
        <truncated>0</truncated>
        <occluded>0</occluded>
        <difficult>0</difficult>
        <bndbox>
            <xmin>2386.403564</xmin>
            <ymin>2174.275391</ymin>
            <xmax>2637.340820</xmax>
            <ymax>2425.191650</ymax>
        </bndbox>
    </object>
    <object>
        <name>spot</name>
        <pose>Unspecified</pose>
        <truncated>0</truncated>
        <occluded>0</occluded>
        <difficult>0</difficult>
        <bndbox>
            <xmin>2665.333740</xmin>
            <ymin>2220.260010</ymin>
            <xmax>2916.270996</xmax>
            <ymax>2471.176270</ymax>
        </bndbox>
    </object>
</annotation>